[
  {
    "game_date": "02/23/2020",
    "location": "Louisville, KY",
    "inning": "1",
    "inning_top_bot": "top",
    "score": "0-0",
    "batting": "Aurora",
    "fielding": "Ohio Northern",
    "description": "Josh Reinhardt fouled out to 1b.",
    "year": 2020,
    "game_pbp_url": "https://stats.ncaa.org/game/play_by_play/4937315",
    "game_pbp_id": 4937315
  },
  {
    "game_date": "02/23/2020",
    "location": "Louisville, KY",
    "inning": "1",
    "inning_top_bot": "top",
    "score": "0-0",
    "batting": "Aurora",
    "fielding": "Ohio Northern",
    "description": "Dylan White struck out looking.",
    "year": 2020,
    "game_pbp_url": "https://stats.ncaa.org/game/play_by_play/4937315",
    "game_pbp_id": 4937315
  },
  {
    "game_date": "02/23/2020",
    "location": "Louisville, KY",
    "inning": "1",
    "inning_top_bot": "top",
    "score": "0-0",
    "batting": "Aurora",
    "fielding": "Ohio Northern",
    "description": "AJ Gill flied out to cf.",
    "year": 2020,
    "game_pbp_url": "https://stats.ncaa.org/game/play_by_play/4937315",
    "game_pbp_id": 4937315
  },
  {
    "game_date": "02/23/2020",
    "location": "Louisville, KY",
    "inning": "1",
    "inning_top_bot": "bot",
    "score": "0-0",
    "batting": "Ohio Northern",
    "fielding": "Aurora",
    "description": "Michael Rocco walked.",
    "year": 2020,
    "game_pbp_url": "https://stats.ncaa.org/game/play_by_play/4937315",
    "game_pbp_id": 4937315
  },
  {
    "game_date": "02/23/2020",
    "location": "Louisville, KY",
    "inning": "1",
    "inning_top_bot": "bot",
    "score": "0-0",
    "batting": "Ohio Northern",
    "fielding": "Aurora",
    "description": "Phil Buckingham grounded into double play p to 1b to ss, SAC, bunt Michael Rocco advanced to second, out on the play.",
    "year": 2020,
    "game_pbp_url": "https://stats.ncaa.org/game/play_by_play/4937315",
    "game_pbp_id": 4937315
  },
  {
    "game_date": "02/23/2020",
    "location": "Louisville, KY",
    "inning": "1",
    "inning_top_bot": "bot",
    "score": "0-0",
    "batting": "Ohio Northern",
    "fielding": "Aurora",
    "description": "Corey McMann singled to center field.",
    "year": 2020,
    "game_pbp_url": "https://stats.ncaa.org/game/play_by_play/4937315",
    "game_pbp_id": 4937315
  },
  {
    "game_date": "02/23/2020",
    "location": "Louisville, KY",
    "inning": "1",
    "inning_top_bot": "bot",
    "score": "0-0",
    "batting": "Ohio Northern",
    "fielding": "Aurora",
    "description": "Matthew Burkett grounded out to p.",
    "year": 2020,
    "game_pbp_url": "https://stats.ncaa.org/game/play_by_play/4937315",
    "game_pbp_id": 4937315
  },
  {
    "game_date": "02/23/2020",
    "location": "Louisville, KY",
    "inning": "2",
    "inning_top_bot": "top",
    "score": "0-0",
    "batting": "Aurora",
    "fielding": "Ohio Northern",
    "description": "Justin Sartori walked.",
    "year": 2020,
    "game_pbp_url": "https://stats.ncaa.org/game/play_by_play/4937315",
    "game_pbp_id": 4937315
  },
  {
    "game_date": "02/23/2020",
    "location": "Louisville, KY",
    "inning": "2",
    "inning_top_bot": "top",
    "score": "0-0",
    "batting": "Aurora",
    "fielding": "Ohio Northern",
    "description": "Jacob Bachio singled to left center Justin Sartori advanced to second.",
    "year": 2020,
    "game_pbp_url": "https://stats.ncaa.org/game/play_by_play/4937315",
    "game_pbp_id": 4937315
  },
  {
    "game_date": "02/23/2020",
    "location": "Louisville, KY",
    "inning": "2",
    "inning_top_bot": "top",
    "score": "0-0",
    "batting": "Aurora",
    "fielding": "Ohio Northern",
    "description": "Colin Rivard struck out looking.",
    "year": 2020,
    "game_pbp_url": "https://stats.ncaa.org/game/play_by_play/4937315",
    "game_pbp_id": 4937315
  },
  {
    "game_date": "02/23/2020",
    "location": "Louisville, KY",
    "inning": "2",
    "inning_top_bot": "top",
    "score": "0-0",
    "batting": "Aurora",
    "fielding": "Ohio Northern",
    "description": "Larsen grounded into double play ss to 2b to 1b Jacob Bachio out on the play.",
    "year": 2020,
    "game_pbp_url": "https://stats.ncaa.org/game/play_by_play/4937315",
    "game_pbp_id": 4937315
  },
  {
    "game_date": "02/23/2020",
    "location": "Louisville, KY",
    "inning": "2",
    "inning_top_bot": "bot",
    "score": "0-0",
    "batting": "Ohio Northern",
    "fielding": "Aurora",
    "description": "Mason Troyer singled through the left side.",
    "year": 2020,
    "game_pbp_url": "https://stats.ncaa.org/game/play_by_play/4937315",
    "game_pbp_id": 4937315
  },
  {
    "game_date": "02/23/2020",
    "location": "Louisville, KY",
    "inning": "2",
    "inning_top_bot": "bot",
    "score": "0-0",
    "batting": "Ohio Northern",
    "fielding": "Aurora",
    "description": "Krue Thwaits struck out swinging.",
    "year": 2020,
    "game_pbp_url": "https://stats.ncaa.org/game/play_by_play/4937315",
    "game_pbp_id": 4937315
  },
  {
    "game_date": "02/23/2020",
    "location": "Louisville, KY",
    "inning": "2",
    "inning_top_bot": "bot",
    "score": "0-0",
    "batting": "Ohio Northern",
    "fielding": "Aurora",
    "description": "Jacob Wenning flied out to cf.",
    "year": 2020,
    "game_pbp_url": "https://stats.ncaa.org/game/play_by_play/4937315",
    "game_pbp_id": 4937315
  },
  {
    "game_date": "02/23/2020",
    "location": "Louisville, KY",
    "inning": "2",
    "inning_top_bot": "bot",
    "score": "0-0",
    "batting": "Ohio Northern",
    "fielding": "Aurora",
    "description": "Sam Zeleznik flied out to cf.",
    "year": 2020,
    "game_pbp_url": "https://stats.ncaa.org/game/play_by_play/4937315",
    "game_pbp_id": 4937315
  },
  {
    "game_date": "02/23/2020",
    "location": "Louisville, KY",
    "inning": "3",
    "inning_top_bot": "top",
    "score": "0-0",
    "batting": "Aurora",
    "fielding": "Ohio Northern",
    "description": "Austin Wiskow walked.",
    "year": 2020,
    "game_pbp_url": "https://stats.ncaa.org/game/play_by_play/4937315",
    "game_pbp_id": 4937315
  },
  {
    "game_date": "02/23/2020",
    "location": "Louisville, KY",
    "inning": "3",
    "inning_top_bot": "top",
    "score": "0-0",
    "batting": "Aurora",
    "fielding": "Ohio Northern",
    "description": "Eric Johansen grounded into double play ss to 2b to 1b Austin Wiskow out on the play.",
    "year": 2020,
    "game_pbp_url": "https://stats.ncaa.org/game/play_by_play/4937315",
    "game_pbp_id": 4937315
  },
  {
    "game_date": "02/23/2020",
    "location": "Louisville, KY",
    "inning": "3",
    "inning_top_bot": "top",
    "score": "0-0",
    "batting": "Aurora",
    "fielding": "Ohio Northern",
    "description": "Josh Reinhardt walked.",
    "year": 2020,
    "game_pbp_url": "https://stats.ncaa.org/game/play_by_play/4937315",
    "game_pbp_id": 4937315
  },
  {
    "game_date": "02/23/2020",
    "location": "Louisville, KY",
    "inning": "3",
    "inning_top_bot": "top",
    "score": "0-0",
    "batting": "Aurora",
    "fielding": "Ohio Northern",
    "description": "Josh Reinhardt advanced to second on a throwing error by p, advanced to third, failed pickoff attempt.",
    "year": 2020,
    "game_pbp_url": "https://stats.ncaa.org/game/play_by_play/4937315",
    "game_pbp_id": 4937315
  },
  {
    "game_date": "02/23/2020",
    "location": "Louisville, KY",
    "inning": "3",
    "inning_top_bot": "top",
    "score": "1-0",
    "batting": "Aurora",
    "fielding": "Ohio Northern",
    "description": "Dylan White singled up the middle, RBI Josh Reinhardt scored, unearned.",
    "year": 2020,
    "game_pbp_url": "https://stats.ncaa.org/game/play_by_play/4937315",
    "game_pbp_id": 4937315
  },
  {
    "game_date": "02/23/2020",
    "location": "Louisville, KY",
    "inning": "3",
    "inning_top_bot": "top",
    "score": "1-0",
    "batting": "Aurora",
    "fielding": "Ohio Northern",
    "description": "AJ Gill doubled down the lf line Dylan White advanced to third.",
    "year": 2020,
    "game_pbp_url": "https://stats.ncaa.org/game/play_by_play/4937315",
    "game_pbp_id": 4937315
  },
  {
    "game_date": "02/23/2020",
    "location": "Louisville, KY",
    "inning": "3",
    "inning_top_bot": "top",
    "score": "2-0",
    "batting": "Aurora",
    "fielding": "Ohio Northern",
    "description": "Justin Sartori reached first on a throwing error by ss AJ Gill advanced to third, out at home 1b to c Dylan White scored, unearned.",
    "year": 2020,
    "game_pbp_url": "https://stats.ncaa.org/game/play_by_play/4937315",
    "game_pbp_id": 4937315
  },
  {
    "game_date": "02/23/2020",
    "location": "Louisville, KY",
    "inning": "3",
    "inning_top_bot": "bot",
    "score": "2-0",
    "batting": "Ohio Northern",
    "fielding": "Aurora",
    "description": "Andy Mills struck out swinging.",
    "year": 2020,
    "game_pbp_url": "https://stats.ncaa.org/game/play_by_play/4937315",
    "game_pbp_id": 4937315
  },
  {
    "game_date": "02/23/2020",
    "location": "Louisville, KY",
    "inning": "3",
    "inning_top_bot": "bot",
    "score": "2-0",
    "batting": "Ohio Northern",
    "fielding": "Aurora",
    "description": "Michael Rocco struck out swinging.",
    "year": 2020,
    "game_pbp_url": "https://stats.ncaa.org/game/play_by_play/4937315",
    "game_pbp_id": 4937315
  },
  {
    "game_date": "02/23/2020",
    "location": "Louisville, KY",
    "inning": "3",
    "inning_top_bot": "bot",
    "score": "2-0",
    "batting": "Ohio Northern",
    "fielding": "Aurora",
    "description": "Phil Buckingham singled through the right side.",
    "year": 2020,
    "game_pbp_url": "https://stats.ncaa.org/game/play_by_play/4937315",
    "game_pbp_id": 4937315
  },
  {
    "game_date": "02/23/2020",
    "location": "Louisville, KY",
    "inning": "3",
    "inning_top_bot": "bot",
    "score": "2-0",
    "batting": "Ohio Northern",
    "fielding": "Aurora",
    "description": "Corey McMann singled through the right side Phil Buckingham advanced to second.",
    "year": 2020,
    "game_pbp_url": "https://stats.ncaa.org/game/play_by_play/4937315",
    "game_pbp_id": 4937315
  },
  {
    "game_date": "02/23/2020",
    "location": "Louisville, KY",
    "inning": "3",
    "inning_top_bot": "bot",
    "score": "2-0",
    "batting": "Ohio Northern",
    "fielding": "Aurora",
    "description": "Matthew Burkett flied out to rf.",
    "year": 2020,
    "game_pbp_url": "https://stats.ncaa.org/game/play_by_play/4937315",
    "game_pbp_id": 4937315
  },
  {
    "game_date": "02/23/2020",
    "location": "Louisville, KY",
    "inning": "4",
    "inning_top_bot": "top",
    "score": "2-0",
    "batting": "Aurora",
    "fielding": "Ohio Northern",
    "description": "Jacob Bachio struck out swinging.",
    "year": 2020,
    "game_pbp_url": "https://stats.ncaa.org/game/play_by_play/4937315",
    "game_pbp_id": 4937315
  },
  {
    "game_date": "02/23/2020",
    "location": "Louisville, KY",
    "inning": "4",
    "inning_top_bot": "top",
    "score": "2-0",
    "batting": "Aurora",
    "fielding": "Ohio Northern",
    "description": "Colin Rivard grounded out to 2b.",
    "year": 2020,
    "game_pbp_url": "https://stats.ncaa.org/game/play_by_play/4937315",
    "game_pbp_id": 4937315
  },
  {
    "game_date": "02/23/2020",
    "location": "Louisville, KY",
    "inning": "4",
    "inning_top_bot": "top",
    "score": "2-0",
    "batting": "Aurora",
    "fielding": "Ohio Northern",
    "description": "Larsen struck out swinging.",
    "year": 2020,
    "game_pbp_url": "https://stats.ncaa.org/game/play_by_play/4937315",
    "game_pbp_id": 4937315
  },
  {
    "game_date": "02/23/2020",
    "location": "Louisville, KY",
    "inning": "4",
    "inning_top_bot": "bot",
    "score": "2-0",
    "batting": "Ohio Northern",
    "fielding": "Aurora",
    "description": "Mason Troyer walked.",
    "year": 2020,
    "game_pbp_url": "https://stats.ncaa.org/game/play_by_play/4937315",
    "game_pbp_id": 4937315
  },
  {
    "game_date": "02/23/2020",
    "location": "Louisville, KY",
    "inning": "4",
    "inning_top_bot": "bot",
    "score": "2-0",
    "batting": "Ohio Northern",
    "fielding": "Aurora",
    "description": "Mason Troyer advanced to second on a wild pitch.",
    "year": 2020,
    "game_pbp_url": "https://stats.ncaa.org/game/play_by_play/4937315",
    "game_pbp_id": 4937315
  },
  {
    "game_date": "02/23/2020",
    "location": "Louisville, KY",
    "inning": "4",
    "inning_top_bot": "bot",
    "score": "2-0",
    "batting": "Ohio Northern",
    "fielding": "Aurora",
    "description": "Krue Thwaits singled to first base Mason Troyer advanced to third.",
    "year": 2020,
    "game_pbp_url": "https://stats.ncaa.org/game/play_by_play/4937315",
    "game_pbp_id": 4937315
  },
  {
    "game_date": "02/23/2020",
    "location": "Louisville, KY",
    "inning": "4",
    "inning_top_bot": "bot",
    "score": "2-1",
    "batting": "Ohio Northern",
    "fielding": "Aurora",
    "description": "Jacob Wenning grounded out to ss, RBI Krue Thwaits advanced to second Mason Troyer scored.",
    "year": 2020,
    "game_pbp_url": "https://stats.ncaa.org/game/play_by_play/4937315",
    "game_pbp_id": 4937315
  },
  {
    "game_date": "02/23/2020",
    "location": "Louisville, KY",
    "inning": "4",
    "inning_top_bot": "bot",
    "score": "2-1",
    "batting": "Ohio Northern",
    "fielding": "Aurora",
    "description": "Sam Zeleznik grounded out to ss Krue Thwaits advanced to third.",
    "year": 2020,
    "game_pbp_url": "https://stats.ncaa.org/game/play_by_play/4937315",
    "game_pbp_id": 4937315
  },
  {
    "game_date": "02/23/2020",
    "location": "Louisville, KY",
    "inning": "4",
    "inning_top_bot": "bot",
    "score": "2-2",
    "batting": "Ohio Northern",
    "fielding": "Aurora",
    "description": "Andy Mills tripled down the lf line, RBI Krue Thwaits scored.",
    "year": 2020,
    "game_pbp_url": "https://stats.ncaa.org/game/play_by_play/4937315",
    "game_pbp_id": 4937315
  },
  {
    "game_date": "02/23/2020",
    "location": "Louisville, KY",
    "inning": "4",
    "inning_top_bot": "bot",
    "score": "2-2",
    "batting": "Ohio Northern",
    "fielding": "Aurora",
    "description": "Michael Rocco grounded out to 3b.",
    "year": 2020,
    "game_pbp_url": "https://stats.ncaa.org/game/play_by_play/4937315",
    "game_pbp_id": 4937315
  },
  {
    "game_date": "02/23/2020",
    "location": "Louisville, KY",
    "inning": "5",
    "inning_top_bot": "top",
    "score": "2-2",
    "batting": "Aurora",
    "fielding": "Ohio Northern",
    "description": "Austin Wiskow walked.",
    "year": 2020,
    "game_pbp_url": "https://stats.ncaa.org/game/play_by_play/4937315",
    "game_pbp_id": 4937315
  },
  {
    "game_date": "02/23/2020",
    "location": "Louisville, KY",
    "inning": "5",
    "inning_top_bot": "top",
    "score": "2-2",
    "batting": "Aurora",
    "fielding": "Ohio Northern",
    "description": "Eric Johansen flied into double play 3b to 1b Austin Wiskow out on the play.",
    "year": 2020,
    "game_pbp_url": "https://stats.ncaa.org/game/play_by_play/4937315",
    "game_pbp_id": 4937315
  },
  {
    "game_date": "02/23/2020",
    "location": "Louisville, KY",
    "inning": "5",
    "inning_top_bot": "top",
    "score": "2-2",
    "batting": "Aurora",
    "fielding": "Ohio Northern",
    "description": "Josh Reinhardt walked.",
    "year": 2020,
    "game_pbp_url": "https://stats.ncaa.org/game/play_by_play/4937315",
    "game_pbp_id": 4937315
  },
  {
    "game_date": "02/23/2020",
    "location": "Louisville, KY",
    "inning": "5",
    "inning_top_bot": "top",
    "score": "2-2",
    "batting": "Aurora",
    "fielding": "Ohio Northern",
    "description": "Dylan White walked Josh Reinhardt advanced to second.",
    "year": 2020,
    "game_pbp_url": "https://stats.ncaa.org/game/play_by_play/4937315",
    "game_pbp_id": 4937315
  },
  {
    "game_date": "02/23/2020",
    "location": "Louisville, KY",
    "inning": "5",
    "inning_top_bot": "top",
    "score": "2-2",
    "batting": "Aurora",
    "fielding": "Ohio Northern",
    "description": "Dylan White advanced to second on an error by p Josh Reinhardt advanced to third.",
    "year": 2020,
    "game_pbp_url": "https://stats.ncaa.org/game/play_by_play/4937315",
    "game_pbp_id": 4937315
  },
  {
    "game_date": "02/23/2020",
    "location": "Louisville, KY",
    "inning": "5",
    "inning_top_bot": "top",
    "score": "2-2",
    "batting": "Aurora",
    "fielding": "Ohio Northern",
    "description": "AJ Gill walked.",
    "year": 2020,
    "game_pbp_url": "https://stats.ncaa.org/game/play_by_play/4937315",
    "game_pbp_id": 4937315
  },
  {
    "game_date": "02/23/2020",
    "location": "Louisville, KY",
    "inning": "5",
    "inning_top_bot": "top",
    "score": "4-2",
    "batting": "Aurora",
    "fielding": "Ohio Northern",
    "description": "Justin Sartori reached first on an error by 3b, advanced to second AJ Gill advanced to third Dylan White scored, unearned Josh Reinhardt scored, unearned.",
    "year": 2020,
    "game_pbp_url": "https://stats.ncaa.org/game/play_by_play/4937315",
    "game_pbp_id": 4937315
  },
  {
    "game_date": "02/23/2020",
    "location": "Louisville, KY",
    "inning": "5",
    "inning_top_bot": "top",
    "score": "4-2",
    "batting": "Aurora",
    "fielding": "Ohio Northern",
    "description": "Scott Beaton to p for Jack Schaller.",
    "year": 2020,
    "game_pbp_url": "https://stats.ncaa.org/game/play_by_play/4937315",
    "game_pbp_id": 4937315
  },
  {
    "game_date": "02/23/2020",
    "location": "Louisville, KY",
    "inning": "5",
    "inning_top_bot": "top",
    "score": "5-2",
    "batting": "Aurora",
    "fielding": "Ohio Northern",
    "description": "Justin Sartori advanced to third AJ Gill scored on a wild pitch, unearned.",
    "year": 2020,
    "game_pbp_url": "https://stats.ncaa.org/game/play_by_play/4937315",
    "game_pbp_id": 4937315
  },
  {
    "game_date": "02/23/2020",
    "location": "Louisville, KY",
    "inning": "5",
    "inning_top_bot": "top",
    "score": "5-2",
    "batting": "Aurora",
    "fielding": "Ohio Northern",
    "description": "Jacob Bachio popped up to 1b.",
    "year": 2020,
    "game_pbp_url": "https://stats.ncaa.org/game/play_by_play/4937315",
    "game_pbp_id": 4937315
  },
  {
    "game_date": "02/23/2020",
    "location": "Louisville, KY",
    "inning": "5",
    "inning_top_bot": "bot",
    "score": "5-2",
    "batting": "Ohio Northern",
    "fielding": "Aurora",
    "description": "Brady Kauppila to p for Nick Malmberg.",
    "year": 2020,
    "game_pbp_url": "https://stats.ncaa.org/game/play_by_play/4937315",
    "game_pbp_id": 4937315
  },
  {
    "game_date": "02/23/2020",
    "location": "Louisville, KY",
    "inning": "5",
    "inning_top_bot": "bot",
    "score": "5-2",
    "batting": "Ohio Northern",
    "fielding": "Aurora",
    "description": "Phil Buckingham walked.",
    "year": 2020,
    "game_pbp_url": "https://stats.ncaa.org/game/play_by_play/4937315",
    "game_pbp_id": 4937315
  },
  {
    "game_date": "02/23/2020",
    "location": "Louisville, KY",
    "inning": "5",
    "inning_top_bot": "bot",
    "score": "5-2",
    "batting": "Ohio Northern",
    "fielding": "Aurora",
    "description": "Corey McMann flied into double play 3b to 1b Phil Buckingham out on the play.",
    "year": 2020,
    "game_pbp_url": "https://stats.ncaa.org/game/play_by_play/4937315",
    "game_pbp_id": 4937315
  },
  {
    "game_date": "02/23/2020",
    "location": "Louisville, KY",
    "inning": "5",
    "inning_top_bot": "bot",
    "score": "5-2",
    "batting": "Ohio Northern",
    "fielding": "Aurora",
    "description": "Matthew Burkett singled to left field.",
    "year": 2020,
    "game_pbp_url": "https://stats.ncaa.org/game/play_by_play/4937315",
    "game_pbp_id": 4937315
  },
  {
    "game_date": "02/23/2020",
    "location": "Louisville, KY",
    "inning": "5",
    "inning_top_bot": "bot",
    "score": "5-2",
    "batting": "Ohio Northern",
    "fielding": "Aurora",
    "description": "Mason Troyer flied out to 1b.",
    "year": 2020,
    "game_pbp_url": "https://stats.ncaa.org/game/play_by_play/4937315",
    "game_pbp_id": 4937315
  },
  {
    "game_date": "02/23/2020",
    "location": "Louisville, KY",
    "inning": "6",
    "inning_top_bot": "top",
    "score": "5-2",
    "batting": "Aurora",
    "fielding": "Ohio Northern",
    "description": "Colin Rivard singled to shortstop.",
    "year": 2020,
    "game_pbp_url": "https://stats.ncaa.org/game/play_by_play/4937315",
    "game_pbp_id": 4937315
  },
  {
    "game_date": "02/23/2020",
    "location": "Louisville, KY",
    "inning": "6",
    "inning_top_bot": "top",
    "score": "5-2",
    "batting": "Aurora",
    "fielding": "Ohio Northern",
    "description": "Larsen reached on a fielders choice Colin Rivard out at second ss to 2b.",
    "year": 2020,
    "game_pbp_url": "https://stats.ncaa.org/game/play_by_play/4937315",
    "game_pbp_id": 4937315
  },
  {
    "game_date": "02/23/2020",
    "location": "Louisville, KY",
    "inning": "6",
    "inning_top_bot": "top",
    "score": "5-2",
    "batting": "Aurora",
    "fielding": "Ohio Northern",
    "description": "Austin Wiskow grounded into double play 2b to ss to 1b Larsen out on the play.",
    "year": 2020,
    "game_pbp_url": "https://stats.ncaa.org/game/play_by_play/4937315",
    "game_pbp_id": 4937315
  },
  {
    "game_date": "02/23/2020",
    "location": "Louisville, KY",
    "inning": "6",
    "inning_top_bot": "bot",
    "score": "5-2",
    "batting": "Ohio Northern",
    "fielding": "Aurora",
    "description": "Krue Thwaits walked.",
    "year": 2020,
    "game_pbp_url": "https://stats.ncaa.org/game/play_by_play/4937315",
    "game_pbp_id": 4937315
  },
  {
    "game_date": "02/23/2020",
    "location": "Louisville, KY",
    "inning": "6",
    "inning_top_bot": "bot",
    "score": "5-2",
    "batting": "Ohio Northern",
    "fielding": "Aurora",
    "description": "Jacob Wenning flied out to 3b.",
    "year": 2020,
    "game_pbp_url": "https://stats.ncaa.org/game/play_by_play/4937315",
    "game_pbp_id": 4937315
  },
  {
    "game_date": "02/23/2020",
    "location": "Louisville, KY",
    "inning": "6",
    "inning_top_bot": "bot",
    "score": "5-2",
    "batting": "Ohio Northern",
    "fielding": "Aurora",
    "description": "Sam Zeleznik struck out swinging.",
    "year": 2020,
    "game_pbp_url": "https://stats.ncaa.org/game/play_by_play/4937315",
    "game_pbp_id": 4937315
  },
  {
    "game_date": "02/23/2020",
    "location": "Louisville, KY",
    "inning": "6",
    "inning_top_bot": "bot",
    "score": "5-2",
    "batting": "Ohio Northern",
    "fielding": "Aurora",
    "description": "Andy Mills singled to shortstop Krue Thwaits advanced to second.",
    "year": 2020,
    "game_pbp_url": "https://stats.ncaa.org/game/play_by_play/4937315",
    "game_pbp_id": 4937315
  },
  {
    "game_date": "02/23/2020",
    "location": "Louisville, KY",
    "inning": "6",
    "inning_top_bot": "bot",
    "score": "5-2",
    "batting": "Ohio Northern",
    "fielding": "Aurora",
    "description": "Michael Rocco flied out to rf.",
    "year": 2020,
    "game_pbp_url": "https://stats.ncaa.org/game/play_by_play/4937315",
    "game_pbp_id": 4937315
  },
  {
    "game_date": "02/23/2020",
    "location": "Louisville, KY",
    "inning": "7",
    "inning_top_bot": "top",
    "score": "5-2",
    "batting": "Aurora",
    "fielding": "Ohio Northern",
    "description": "Troy Wagner to p for Scott Beaton.",
    "year": 2020,
    "game_pbp_url": "https://stats.ncaa.org/game/play_by_play/4937315",
    "game_pbp_id": 4937315
  },
  {
    "game_date": "02/23/2020",
    "location": "Louisville, KY",
    "inning": "7",
    "inning_top_bot": "top",
    "score": "5-2",
    "batting": "Aurora",
    "fielding": "Ohio Northern",
    "description": "Eric Johansen flied out to cf.",
    "year": 2020,
    "game_pbp_url": "https://stats.ncaa.org/game/play_by_play/4937315",
    "game_pbp_id": 4937315
  },
  {
    "game_date": "02/23/2020",
    "location": "Louisville, KY",
    "inning": "7",
    "inning_top_bot": "top",
    "score": "5-2",
    "batting": "Aurora",
    "fielding": "Ohio Northern",
    "description": "Josh Reinhardt doubled to left field.",
    "year": 2020,
    "game_pbp_url": "https://stats.ncaa.org/game/play_by_play/4937315",
    "game_pbp_id": 4937315
  },
  {
    "game_date": "02/23/2020",
    "location": "Louisville, KY",
    "inning": "7",
    "inning_top_bot": "top",
    "score": "5-2",
    "batting": "Aurora",
    "fielding": "Ohio Northern",
    "description": "Dylan White grounded out to 3b.",
    "year": 2020,
    "game_pbp_url": "https://stats.ncaa.org/game/play_by_play/4937315",
    "game_pbp_id": 4937315
  },
  {
    "game_date": "02/23/2020",
    "location": "Louisville, KY",
    "inning": "7",
    "inning_top_bot": "top",
    "score": "5-2",
    "batting": "Aurora",
    "fielding": "Ohio Northern",
    "description": "AJ Gill flied out to lf.",
    "year": 2020,
    "game_pbp_url": "https://stats.ncaa.org/game/play_by_play/4937315",
    "game_pbp_id": 4937315
  },
  {
    "game_date": "02/23/2020",
    "location": "Louisville, KY",
    "inning": "7",
    "inning_top_bot": "bot",
    "score": "5-2",
    "batting": "Ohio Northern",
    "fielding": "Aurora",
    "description": "Josh Reinhardt to p.",
    "year": 2020,
    "game_pbp_url": "https://stats.ncaa.org/game/play_by_play/4937315",
    "game_pbp_id": 4937315
  },
  {
    "game_date": "02/23/2020",
    "location": "Louisville, KY",
    "inning": "7",
    "inning_top_bot": "bot",
    "score": "5-2",
    "batting": "Ohio Northern",
    "fielding": "Aurora",
    "description": "Nick Baldassano to dh for Jacob Bachio.",
    "year": 2020,
    "game_pbp_url": "https://stats.ncaa.org/game/play_by_play/4937315",
    "game_pbp_id": 4937315
  },
  {
    "game_date": "02/23/2020",
    "location": "Louisville, KY",
    "inning": "7",
    "inning_top_bot": "bot",
    "score": "5-2",
    "batting": "Ohio Northern",
    "fielding": "Aurora",
    "description": "Austin Wiskow to ss.",
    "year": 2020,
    "game_pbp_url": "https://stats.ncaa.org/game/play_by_play/4937315",
    "game_pbp_id": 4937315
  },
  {
    "game_date": "02/23/2020",
    "location": "Louisville, KY",
    "inning": "7",
    "inning_top_bot": "bot",
    "score": "5-2",
    "batting": "Ohio Northern",
    "fielding": "Aurora",
    "description": "for Brady Kauppila.",
    "year": 2020,
    "game_pbp_url": "https://stats.ncaa.org/game/play_by_play/4937315",
    "game_pbp_id": 4937315
  },
  {
    "game_date": "02/23/2020",
    "location": "Louisville, KY",
    "inning": "7",
    "inning_top_bot": "bot",
    "score": "5-2",
    "batting": "Ohio Northern",
    "fielding": "Aurora",
    "description": "Jett Wedekind to c for Nick Baldassano.",
    "year": 2020,
    "game_pbp_url": "https://stats.ncaa.org/game/play_by_play/4937315",
    "game_pbp_id": 4937315
  },
  {
    "game_date": "02/23/2020",
    "location": "Louisville, KY",
    "inning": "7",
    "inning_top_bot": "bot",
    "score": "5-2",
    "batting": "Ohio Northern",
    "fielding": "Aurora",
    "description": "Nick Baldassano to 2b for Eric Johansen.",
    "year": 2020,
    "game_pbp_url": "https://stats.ncaa.org/game/play_by_play/4937315",
    "game_pbp_id": 4937315
  },
  {
    "game_date": "02/23/2020",
    "location": "Louisville, KY",
    "inning": "7",
    "inning_top_bot": "bot",
    "score": "5-2",
    "batting": "Ohio Northern",
    "fielding": "Aurora",
    "description": "Phil Buckingham grounded out to 2b.",
    "year": 2020,
    "game_pbp_url": "https://stats.ncaa.org/game/play_by_play/4937315",
    "game_pbp_id": 4937315
  },
  {
    "game_date": "02/23/2020",
    "location": "Louisville, KY",
    "inning": "7",
    "inning_top_bot": "bot",
    "score": "5-2",
    "batting": "Ohio Northern",
    "fielding": "Aurora",
    "description": "Corey McMann struck out swinging.",
    "year": 2020,
    "game_pbp_url": "https://stats.ncaa.org/game/play_by_play/4937315",
    "game_pbp_id": 4937315
  },
  {
    "game_date": "02/23/2020",
    "location": "Louisville, KY",
    "inning": "7",
    "inning_top_bot": "bot",
    "score": "5-2",
    "batting": "Ohio Northern",
    "fielding": "Aurora",
    "description": "Matthew Burkett grounded out to ss.",
    "year": 2020,
    "game_pbp_url": "https://stats.ncaa.org/game/play_by_play/4937315",
    "game_pbp_id": 4937315
  },
  {
    "game_date": "02/23/2020",
    "location": "Louisville, KY",
    "inning": "8",
    "inning_top_bot": "top",
    "score": "5-2",
    "batting": "Aurora",
    "fielding": "Ohio Northern",
    "description": "Justin Sartori flied out to rf.",
    "year": 2020,
    "game_pbp_url": "https://stats.ncaa.org/game/play_by_play/4937315",
    "game_pbp_id": 4937315
  },
  {
    "game_date": "02/23/2020",
    "location": "Louisville, KY",
    "inning": "8",
    "inning_top_bot": "top",
    "score": "5-2",
    "batting": "Aurora",
    "fielding": "Ohio Northern",
    "description": "Jett Wedekind flied out to lf.",
    "year": 2020,
    "game_pbp_url": "https://stats.ncaa.org/game/play_by_play/4937315",
    "game_pbp_id": 4937315
  },
  {
    "game_date": "02/23/2020",
    "location": "Louisville, KY",
    "inning": "8",
    "inning_top_bot": "top",
    "score": "5-2",
    "batting": "Aurora",
    "fielding": "Ohio Northern",
    "description": "Colin Rivard singled to left field.",
    "year": 2020,
    "game_pbp_url": "https://stats.ncaa.org/game/play_by_play/4937315",
    "game_pbp_id": 4937315
  },
  {
    "game_date": "02/23/2020",
    "location": "Louisville, KY",
    "inning": "8",
    "inning_top_bot": "top",
    "score": "5-2",
    "batting": "Aurora",
    "fielding": "Ohio Northern",
    "description": "Colin Rivard out at second c to ss, caught stealing.",
    "year": 2020,
    "game_pbp_url": "https://stats.ncaa.org/game/play_by_play/4937315",
    "game_pbp_id": 4937315
  },
  {
    "game_date": "02/23/2020",
    "location": "Louisville, KY",
    "inning": "8",
    "inning_top_bot": "bot",
    "score": "5-2",
    "batting": "Ohio Northern",
    "fielding": "Aurora",
    "description": "Mason Troyer grounded out to ss.",
    "year": 2020,
    "game_pbp_url": "https://stats.ncaa.org/game/play_by_play/4937315",
    "game_pbp_id": 4937315
  },
  {
    "game_date": "02/23/2020",
    "location": "Louisville, KY",
    "inning": "8",
    "inning_top_bot": "bot",
    "score": "5-2",
    "batting": "Ohio Northern",
    "fielding": "Aurora",
    "description": "Krue Thwaits singled to right center.",
    "year": 2020,
    "game_pbp_url": "https://stats.ncaa.org/game/play_by_play/4937315",
    "game_pbp_id": 4937315
  },
  {
    "game_date": "02/23/2020",
    "location": "Louisville, KY",
    "inning": "8",
    "inning_top_bot": "bot",
    "score": "5-2",
    "batting": "Ohio Northern",
    "fielding": "Aurora",
    "description": "Jacob Wenning fouled out to c.",
    "year": 2020,
    "game_pbp_url": "https://stats.ncaa.org/game/play_by_play/4937315",
    "game_pbp_id": 4937315
  },
  {
    "game_date": "02/23/2020",
    "location": "Louisville, KY",
    "inning": "8",
    "inning_top_bot": "bot",
    "score": "5-2",
    "batting": "Ohio Northern",
    "fielding": "Aurora",
    "description": "Sam Zeleznik singled to right center Krue Thwaits advanced to second.",
    "year": 2020,
    "game_pbp_url": "https://stats.ncaa.org/game/play_by_play/4937315",
    "game_pbp_id": 4937315
  },
  {
    "game_date": "02/23/2020",
    "location": "Louisville, KY",
    "inning": "8",
    "inning_top_bot": "bot",
    "score": "5-2",
    "batting": "Ohio Northern",
    "fielding": "Aurora",
    "description": "Andy Mills singled up the middle Sam Zeleznik advanced to second Krue Thwaits advanced to third.",
    "year": 2020,
    "game_pbp_url": "https://stats.ncaa.org/game/play_by_play/4937315",
    "game_pbp_id": 4937315
  },
  {
    "game_date": "02/23/2020",
    "location": "Louisville, KY",
    "inning": "8",
    "inning_top_bot": "bot",
    "score": "5-2",
    "batting": "Ohio Northern",
    "fielding": "Aurora",
    "description": "Michael Rocco struck out swinging.",
    "year": 2020,
    "game_pbp_url": "https://stats.ncaa.org/game/play_by_play/4937315",
    "game_pbp_id": 4937315
  },
  {
    "game_date": "02/23/2020",
    "location": "Louisville, KY",
    "inning": "9",
    "inning_top_bot": "top",
    "score": "5-2",
    "batting": "Aurora",
    "fielding": "Ohio Northern",
    "description": "Larsen grounded out to 3b.",
    "year": 2020,
    "game_pbp_url": "https://stats.ncaa.org/game/play_by_play/4937315",
    "game_pbp_id": 4937315
  },
  {
    "game_date": "02/23/2020",
    "location": "Louisville, KY",
    "inning": "9",
    "inning_top_bot": "top",
    "score": "5-2",
    "batting": "Aurora",
    "fielding": "Ohio Northern",
    "description": "Austin Wiskow lined out to 1b.",
    "year": 2020,
    "game_pbp_url": "https://stats.ncaa.org/game/play_by_play/4937315",
    "game_pbp_id": 4937315
  },
  {
    "game_date": "02/23/2020",
    "location": "Louisville, KY",
    "inning": "9",
    "inning_top_bot": "top",
    "score": "5-2",
    "batting": "Aurora",
    "fielding": "Ohio Northern",
    "description": "Nick Baldassano singled to left field.",
    "year": 2020,
    "game_pbp_url": "https://stats.ncaa.org/game/play_by_play/4937315",
    "game_pbp_id": 4937315
  },
  {
    "game_date": "02/23/2020",
    "location": "Louisville, KY",
    "inning": "9",
    "inning_top_bot": "top",
    "score": "5-2",
    "batting": "Aurora",
    "fielding": "Ohio Northern",
    "description": "Nick Baldassano advanced to second on a wild pitch.",
    "year": 2020,
    "game_pbp_url": "https://stats.ncaa.org/game/play_by_play/4937315",
    "game_pbp_id": 4937315
  },
  {
    "game_date": "02/23/2020",
    "location": "Louisville, KY",
    "inning": "9",
    "inning_top_bot": "top",
    "score": "5-2",
    "batting": "Aurora",
    "fielding": "Ohio Northern",
    "description": "Nick Baldassano advanced to third on a wild pitch.",
    "year": 2020,
    "game_pbp_url": "https://stats.ncaa.org/game/play_by_play/4937315",
    "game_pbp_id": 4937315
  },
  {
    "game_date": "02/23/2020",
    "location": "Louisville, KY",
    "inning": "9",
    "inning_top_bot": "top",
    "score": "5-2",
    "batting": "Aurora",
    "fielding": "Ohio Northern",
    "description": "Josh Reinhardt walked.",
    "year": 2020,
    "game_pbp_url": "https://stats.ncaa.org/game/play_by_play/4937315",
    "game_pbp_id": 4937315
  },
  {
    "game_date": "02/23/2020",
    "location": "Louisville, KY",
    "inning": "9",
    "inning_top_bot": "top",
    "score": "5-2",
    "batting": "Aurora",
    "fielding": "Ohio Northern",
    "description": "Josh Reinhardt stole second.",
    "year": 2020,
    "game_pbp_url": "https://stats.ncaa.org/game/play_by_play/4937315",
    "game_pbp_id": 4937315
  },
  {
    "game_date": "02/23/2020",
    "location": "Louisville, KY",
    "inning": "9",
    "inning_top_bot": "top",
    "score": "5-2",
    "batting": "Aurora",
    "fielding": "Ohio Northern",
    "description": "Dylan White struck out looking.",
    "year": 2020,
    "game_pbp_url": "https://stats.ncaa.org/game/play_by_play/4937315",
    "game_pbp_id": 4937315
  },
  {
    "game_date": "02/23/2020",
    "location": "Louisville, KY",
    "inning": "9",
    "inning_top_bot": "bot",
    "score": "5-2",
    "batting": "Ohio Northern",
    "fielding": "Aurora",
    "description": "Blake Milburn to lf for AJ Gill.",
    "year": 2020,
    "game_pbp_url": "https://stats.ncaa.org/game/play_by_play/4937315",
    "game_pbp_id": 4937315
  },
  {
    "game_date": "02/23/2020",
    "location": "Louisville, KY",
    "inning": "9",
    "inning_top_bot": "bot",
    "score": "5-2",
    "batting": "Ohio Northern",
    "fielding": "Aurora",
    "description": "Seth Gutknecht to p for Josh Reinhardt.",
    "year": 2020,
    "game_pbp_url": "https://stats.ncaa.org/game/play_by_play/4937315",
    "game_pbp_id": 4937315
  },
  {
    "game_date": "02/23/2020",
    "location": "Louisville, KY",
    "inning": "9",
    "inning_top_bot": "bot",
    "score": "5-2",
    "batting": "Ohio Northern",
    "fielding": "Aurora",
    "description": "Phil Buckingham lined out to rf.",
    "year": 2020,
    "game_pbp_url": "https://stats.ncaa.org/game/play_by_play/4937315",
    "game_pbp_id": 4937315
  },
  {
    "game_date": "02/23/2020",
    "location": "Louisville, KY",
    "inning": "9",
    "inning_top_bot": "bot",
    "score": "5-2",
    "batting": "Ohio Northern",
    "fielding": "Aurora",
    "description": "Corey McMann doubled down the lf line.",
    "year": 2020,
    "game_pbp_url": "https://stats.ncaa.org/game/play_by_play/4937315",
    "game_pbp_id": 4937315
  },
  {
    "game_date": "02/23/2020",
    "location": "Louisville, KY",
    "inning": "9",
    "inning_top_bot": "bot",
    "score": "5-4",
    "batting": "Ohio Northern",
    "fielding": "Aurora",
    "description": "Matthew Burkett homered to left field, 2 RBI Corey McMann scored.",
    "year": 2020,
    "game_pbp_url": "https://stats.ncaa.org/game/play_by_play/4937315",
    "game_pbp_id": 4937315
  },
  {
    "game_date": "02/23/2020",
    "location": "Louisville, KY",
    "inning": "9",
    "inning_top_bot": "bot",
    "score": "5-4",
    "batting": "Ohio Northern",
    "fielding": "Aurora",
    "description": "Mason Troyer struck out swinging.",
    "year": 2020,
    "game_pbp_url": "https://stats.ncaa.org/game/play_by_play/4937315",
    "game_pbp_id": 4937315
  },
  {
    "game_date": "02/23/2020",
    "location": "Louisville, KY",
    "inning": "9",
    "inning_top_bot": "bot",
    "score": "5-4",
    "batting": "Ohio Northern",
    "fielding": "Aurora",
    "description": "Krue Thwaits struck out swinging.",
    "year": 2020,
    "game_pbp_url": "https://stats.ncaa.org/game/play_by_play/4937315",
    "game_pbp_id": 4937315
  }
]

