[
  {
    "game_date": "02/19/2022",
    "location": "Greensboro, NC",
    "inning": "1",
    "inning_top_bot": "top",
    "score": "0-0",
    "batting": "Dayton",
    "fielding": "N.C. A&T",
    "description": "MARTINEZ struck out looking.",
    "year": 2022,
    "game_pbp_url": "https://stats.ncaa.org/game/play_by_play/5209055",
    "game_pbp_id": 5209055
  },
  {
    "game_date": "02/19/2022",
    "location": "Greensboro, NC",
    "inning": "1",
    "inning_top_bot": "top",
    "score": "0-0",
    "batting": "Dayton",
    "fielding": "N.C. A&T",
    "description": "JONES singled to second base.",
    "year": 2022,
    "game_pbp_url": "https://stats.ncaa.org/game/play_by_play/5209055",
    "game_pbp_id": 5209055
  },
  {
    "game_date": "02/19/2022",
    "location": "Greensboro, NC",
    "inning": "1",
    "inning_top_bot": "top",
    "score": "0-0",
    "batting": "Dayton",
    "fielding": "N.C. A&T",
    "description": "JONES out at second c to ss, caught stealing.",
    "year": 2022,
    "game_pbp_url": "https://stats.ncaa.org/game/play_by_play/5209055",
    "game_pbp_id": 5209055
  },
  {
    "game_date": "02/19/2022",
    "location": "Greensboro, NC",
    "inning": "1",
    "inning_top_bot": "top",
    "score": "0-0",
    "batting": "Dayton",
    "fielding": "N.C. A&T",
    "description": "PUJOLS struck out swinging.",
    "year": 2022,
    "game_pbp_url": "https://stats.ncaa.org/game/play_by_play/5209055",
    "game_pbp_id": 5209055
  },
  {
    "game_date": "02/19/2022",
    "location": "Greensboro, NC",
    "inning": "1",
    "inning_top_bot": "top",
    "score": "0-0",
    "batting": "Dayton",
    "fielding": "N.C. A&T",
    "description": "H: 1",
    "year": 2022,
    "game_pbp_url": "https://stats.ncaa.org/game/play_by_play/5209055",
    "game_pbp_id": 5209055
  },
  {
    "game_date": "02/19/2022",
    "location": "Greensboro, NC",
    "inning": "1",
    "inning_top_bot": "bot",
    "score": "0-0",
    "batting": "N.C. A&T",
    "fielding": "Dayton",
    "description": "BRANTLEY, C. struck out swinging, reached first on a wild pitch.",
    "year": 2022,
    "game_pbp_url": "https://stats.ncaa.org/game/play_by_play/5209055",
    "game_pbp_id": 5209055
  },
  {
    "game_date": "02/19/2022",
    "location": "Greensboro, NC",
    "inning": "1",
    "inning_top_bot": "bot",
    "score": "0-0",
    "batting": "N.C. A&T",
    "fielding": "Dayton",
    "description": "MAYNARD, C. struck out swinging.",
    "year": 2022,
    "game_pbp_url": "https://stats.ncaa.org/game/play_by_play/5209055",
    "game_pbp_id": 5209055
  },
  {
    "game_date": "02/19/2022",
    "location": "Greensboro, NC",
    "inning": "1",
    "inning_top_bot": "bot",
    "score": "0-0",
    "batting": "N.C. A&T",
    "fielding": "Dayton",
    "description": "JACKSON, C. walked3a BRANTLEY, C. advanced to second.",
    "year": 2022,
    "game_pbp_url": "https://stats.ncaa.org/game/play_by_play/5209055",
    "game_pbp_id": 5209055
  },
  {
    "game_date": "02/19/2022",
    "location": "Greensboro, NC",
    "inning": "1",
    "inning_top_bot": "bot",
    "score": "0-0",
    "batting": "N.C. A&T",
    "fielding": "Dayton",
    "description": "BUSSEY, X. struck out swinging.",
    "year": 2022,
    "game_pbp_url": "https://stats.ncaa.org/game/play_by_play/5209055",
    "game_pbp_id": 5209055
  },
  {
    "game_date": "02/19/2022",
    "location": "Greensboro, NC",
    "inning": "1",
    "inning_top_bot": "bot",
    "score": "0-0",
    "batting": "N.C. A&T",
    "fielding": "Dayton",
    "description": "BARRETT, T. struck out swinging, grounded out to c unassisted.",
    "year": 2022,
    "game_pbp_url": "https://stats.ncaa.org/game/play_by_play/5209055",
    "game_pbp_id": 5209055
  },
  {
    "game_date": "02/19/2022",
    "location": "Greensboro, NC",
    "inning": "1",
    "inning_top_bot": "top",
    "score": "0-0",
    "batting": "Dayton",
    "fielding": "N.C. A&T",
    "description": "LOB: 2",
    "year": 2022,
    "game_pbp_url": "https://stats.ncaa.org/game/play_by_play/5209055",
    "game_pbp_id": 5209055
  },
  {
    "game_date": "02/19/2022",
    "location": "Greensboro, NC",
    "inning": "2",
    "inning_top_bot": "top",
    "score": "0-0",
    "batting": "Dayton",
    "fielding": "N.C. A&T",
    "description": "STRMECKI doubled to left center.",
    "year": 2022,
    "game_pbp_url": "https://stats.ncaa.org/game/play_by_play/5209055",
    "game_pbp_id": 5209055
  },
  {
    "game_date": "02/19/2022",
    "location": "Greensboro, NC",
    "inning": "2",
    "inning_top_bot": "top",
    "score": "0-0",
    "batting": "Dayton",
    "fielding": "N.C. A&T",
    "description": "NEFF walked.",
    "year": 2022,
    "game_pbp_url": "https://stats.ncaa.org/game/play_by_play/5209055",
    "game_pbp_id": 5209055
  },
  {
    "game_date": "02/19/2022",
    "location": "Greensboro, NC",
    "inning": "2",
    "inning_top_bot": "top",
    "score": "0-0",
    "batting": "Dayton",
    "fielding": "N.C. A&T",
    "description": "CURTIS flied out to cf3a NEFF no advance3a STRMECKI advanced to third.",
    "year": 2022,
    "game_pbp_url": "https://stats.ncaa.org/game/play_by_play/5209055",
    "game_pbp_id": 5209055
  },
  {
    "game_date": "02/19/2022",
    "location": "Greensboro, NC",
    "inning": "2",
    "inning_top_bot": "top",
    "score": "1-0",
    "batting": "Dayton",
    "fielding": "N.C. A&T",
    "description": "CASTILLO struck out swinging3a NEFF stole second3a STRMECKI scored on the throw.",
    "year": 2022,
    "game_pbp_url": "https://stats.ncaa.org/game/play_by_play/5209055",
    "game_pbp_id": 5209055
  },
  {
    "game_date": "02/19/2022",
    "location": "Greensboro, NC",
    "inning": "2",
    "inning_top_bot": "top",
    "score": "1-0",
    "batting": "Dayton",
    "fielding": "N.C. A&T",
    "description": "NEFF out at third c to 3b, caught stealing.",
    "year": 2022,
    "game_pbp_url": "https://stats.ncaa.org/game/play_by_play/5209055",
    "game_pbp_id": 5209055
  },
  {
    "game_date": "02/19/2022",
    "location": "Greensboro, NC",
    "inning": "2",
    "inning_top_bot": "bot",
    "score": "1-0",
    "batting": "N.C. A&T",
    "fielding": "Dayton",
    "description": "SIKES, C. doubled to left center.",
    "year": 2022,
    "game_pbp_url": "https://stats.ncaa.org/game/play_by_play/5209055",
    "game_pbp_id": 5209055
  },
  {
    "game_date": "02/19/2022",
    "location": "Greensboro, NC",
    "inning": "2",
    "inning_top_bot": "bot",
    "score": "1-1",
    "batting": "N.C. A&T",
    "fielding": "Dayton",
    "description": "SEATON, A. reached on a throwing error by p, SAC, advanced to second3a SIKES, C. scored, unearned.",
    "year": 2022,
    "game_pbp_url": "https://stats.ncaa.org/game/play_by_play/5209055",
    "game_pbp_id": 5209055
  },
  {
    "game_date": "02/19/2022",
    "location": "Greensboro, NC",
    "inning": "2",
    "inning_top_bot": "bot",
    "score": "1-1",
    "batting": "N.C. A&T",
    "fielding": "Dayton",
    "description": "REYNA, A. grounded out to 3b, bunt, SAC3a SEATON, A. advanced to third.",
    "year": 2022,
    "game_pbp_url": "https://stats.ncaa.org/game/play_by_play/5209055",
    "game_pbp_id": 5209055
  },
  {
    "game_date": "02/19/2022",
    "location": "Greensboro, NC",
    "inning": "2",
    "inning_top_bot": "bot",
    "score": "1-1",
    "batting": "N.C. A&T",
    "fielding": "Dayton",
    "description": "BROWN, C. hit by pitch.",
    "year": 2022,
    "game_pbp_url": "https://stats.ncaa.org/game/play_by_play/5209055",
    "game_pbp_id": 5209055
  },
  {
    "game_date": "02/19/2022",
    "location": "Greensboro, NC",
    "inning": "2",
    "inning_top_bot": "bot",
    "score": "1-1",
    "batting": "N.C. A&T",
    "fielding": "Dayton",
    "description": "BROWN, C. out at second c to 2b, caught stealing.",
    "year": 2022,
    "game_pbp_url": "https://stats.ncaa.org/game/play_by_play/5209055",
    "game_pbp_id": 5209055
  },
  {
    "game_date": "02/19/2022",
    "location": "Greensboro, NC",
    "inning": "2",
    "inning_top_bot": "bot",
    "score": "1-1",
    "batting": "N.C. A&T",
    "fielding": "Dayton",
    "description": "BRANTLEY, C. walked.",
    "year": 2022,
    "game_pbp_url": "https://stats.ncaa.org/game/play_by_play/5209055",
    "game_pbp_id": 5209055
  },
  {
    "game_date": "02/19/2022",
    "location": "Greensboro, NC",
    "inning": "2",
    "inning_top_bot": "bot",
    "score": "1-1",
    "batting": "N.C. A&T",
    "fielding": "Dayton",
    "description": "MAYNARD, C. hit by pitch3a BRANTLEY, C. advanced to second.",
    "year": 2022,
    "game_pbp_url": "https://stats.ncaa.org/game/play_by_play/5209055",
    "game_pbp_id": 5209055
  },
  {
    "game_date": "02/19/2022",
    "location": "Greensboro, NC",
    "inning": "2",
    "inning_top_bot": "bot",
    "score": "1-1",
    "batting": "N.C. A&T",
    "fielding": "Dayton",
    "description": "JACKSON, C. flied out to lf.",
    "year": 2022,
    "game_pbp_url": "https://stats.ncaa.org/game/play_by_play/5209055",
    "game_pbp_id": 5209055
  },
  {
    "game_date": "02/19/2022",
    "location": "Greensboro, NC",
    "inning": "3",
    "inning_top_bot": "top",
    "score": "1-1",
    "batting": "Dayton",
    "fielding": "N.C. A&T",
    "description": "CALERO doubled to right field.",
    "year": 2022,
    "game_pbp_url": "https://stats.ncaa.org/game/play_by_play/5209055",
    "game_pbp_id": 5209055
  },
  {
    "game_date": "02/19/2022",
    "location": "Greensboro, NC",
    "inning": "3",
    "inning_top_bot": "top",
    "score": "1-1",
    "batting": "Dayton",
    "fielding": "N.C. A&T",
    "description": "DANIELS hit by pitch.",
    "year": 2022,
    "game_pbp_url": "https://stats.ncaa.org/game/play_by_play/5209055",
    "game_pbp_id": 5209055
  },
  {
    "game_date": "02/19/2022",
    "location": "Greensboro, NC",
    "inning": "3",
    "inning_top_bot": "top",
    "score": "1-1",
    "batting": "Dayton",
    "fielding": "N.C. A&T",
    "description": "DANIELS out at first p to 1b, picked off.",
    "year": 2022,
    "game_pbp_url": "https://stats.ncaa.org/game/play_by_play/5209055",
    "game_pbp_id": 5209055
  },
  {
    "game_date": "02/19/2022",
    "location": "Greensboro, NC",
    "inning": "3",
    "inning_top_bot": "top",
    "score": "1-1",
    "batting": "Dayton",
    "fielding": "N.C. A&T",
    "description": "CALERO advanced to third on a wild pitch.",
    "year": 2022,
    "game_pbp_url": "https://stats.ncaa.org/game/play_by_play/5209055",
    "game_pbp_id": 5209055
  },
  {
    "game_date": "02/19/2022",
    "location": "Greensboro, NC",
    "inning": "3",
    "inning_top_bot": "top",
    "score": "2-1",
    "batting": "Dayton",
    "fielding": "N.C. A&T",
    "description": "CALERO scored on a throwing error by c, unearned.",
    "year": 2022,
    "game_pbp_url": "https://stats.ncaa.org/game/play_by_play/5209055",
    "game_pbp_id": 5209055
  },
  {
    "game_date": "02/19/2022",
    "location": "Greensboro, NC",
    "inning": "3",
    "inning_top_bot": "top",
    "score": "2-1",
    "batting": "Dayton",
    "fielding": "N.C. A&T",
    "description": "MARTINEZ walked.",
    "year": 2022,
    "game_pbp_url": "https://stats.ncaa.org/game/play_by_play/5209055",
    "game_pbp_id": 5209055
  },
  {
    "game_date": "02/19/2022",
    "location": "Greensboro, NC",
    "inning": "3",
    "inning_top_bot": "top",
    "score": "3-1",
    "batting": "Dayton",
    "fielding": "N.C. A&T",
    "description": "JONES doubled, RBI3a MARTINEZ scored.",
    "year": 2022,
    "game_pbp_url": "https://stats.ncaa.org/game/play_by_play/5209055",
    "game_pbp_id": 5209055
  },
  {
    "game_date": "02/19/2022",
    "location": "Greensboro, NC",
    "inning": "3",
    "inning_top_bot": "top",
    "score": "4-1",
    "batting": "Dayton",
    "fielding": "N.C. A&T",
    "description": "PUJOLS doubled, RBI3a JONES scored.",
    "year": 2022,
    "game_pbp_url": "https://stats.ncaa.org/game/play_by_play/5209055",
    "game_pbp_id": 5209055
  },
  {
    "game_date": "02/19/2022",
    "location": "Greensboro, NC",
    "inning": "3",
    "inning_top_bot": "top",
    "score": "4-1",
    "batting": "Dayton",
    "fielding": "N.C. A&T",
    "description": "PUJOLS advanced to third on a wild pitch.",
    "year": 2022,
    "game_pbp_url": "https://stats.ncaa.org/game/play_by_play/5209055",
    "game_pbp_id": 5209055
  },
  {
    "game_date": "02/19/2022",
    "location": "Greensboro, NC",
    "inning": "3",
    "inning_top_bot": "top",
    "score": "4-1",
    "batting": "Dayton",
    "fielding": "N.C. A&T",
    "description": "HULL, J. to p for JAROSZ, L..",
    "year": 2022,
    "game_pbp_url": "https://stats.ncaa.org/game/play_by_play/5209055",
    "game_pbp_id": 5209055
  },
  {
    "game_date": "02/19/2022",
    "location": "Greensboro, NC",
    "inning": "3",
    "inning_top_bot": "top",
    "score": "4-1",
    "batting": "Dayton",
    "fielding": "N.C. A&T",
    "description": "STRMECKI walked.",
    "year": 2022,
    "game_pbp_url": "https://stats.ncaa.org/game/play_by_play/5209055",
    "game_pbp_id": 5209055
  },
  {
    "game_date": "02/19/2022",
    "location": "Greensboro, NC",
    "inning": "3",
    "inning_top_bot": "top",
    "score": "4-1",
    "batting": "Dayton",
    "fielding": "N.C. A&T",
    "description": "NEFF walked3a STRMECKI advanced to second.",
    "year": 2022,
    "game_pbp_url": "https://stats.ncaa.org/game/play_by_play/5209055",
    "game_pbp_id": 5209055
  },
  {
    "game_date": "02/19/2022",
    "location": "Greensboro, NC",
    "inning": "3",
    "inning_top_bot": "top",
    "score": "4-1",
    "batting": "Dayton",
    "fielding": "N.C. A&T",
    "description": "CURTIS struck out swinging.",
    "year": 2022,
    "game_pbp_url": "https://stats.ncaa.org/game/play_by_play/5209055",
    "game_pbp_id": 5209055
  },
  {
    "game_date": "02/19/2022",
    "location": "Greensboro, NC",
    "inning": "3",
    "inning_top_bot": "top",
    "score": "4-1",
    "batting": "Dayton",
    "fielding": "N.C. A&T",
    "description": "CASTILLO struck out swinging.",
    "year": 2022,
    "game_pbp_url": "https://stats.ncaa.org/game/play_by_play/5209055",
    "game_pbp_id": 5209055
  },
  {
    "game_date": "02/19/2022",
    "location": "Greensboro, NC",
    "inning": "3",
    "inning_top_bot": "bot",
    "score": "4-1",
    "batting": "N.C. A&T",
    "fielding": "Dayton",
    "description": "BUSSEY, X. lined out to lf.",
    "year": 2022,
    "game_pbp_url": "https://stats.ncaa.org/game/play_by_play/5209055",
    "game_pbp_id": 5209055
  },
  {
    "game_date": "02/19/2022",
    "location": "Greensboro, NC",
    "inning": "3",
    "inning_top_bot": "bot",
    "score": "4-1",
    "batting": "N.C. A&T",
    "fielding": "Dayton",
    "description": "BARRETT, T. grounded out to ss.",
    "year": 2022,
    "game_pbp_url": "https://stats.ncaa.org/game/play_by_play/5209055",
    "game_pbp_id": 5209055
  },
  {
    "game_date": "02/19/2022",
    "location": "Greensboro, NC",
    "inning": "3",
    "inning_top_bot": "bot",
    "score": "4-1",
    "batting": "N.C. A&T",
    "fielding": "Dayton",
    "description": "SIKES, C. doubled down the lf line.",
    "year": 2022,
    "game_pbp_url": "https://stats.ncaa.org/game/play_by_play/5209055",
    "game_pbp_id": 5209055
  },
  {
    "game_date": "02/19/2022",
    "location": "Greensboro, NC",
    "inning": "3",
    "inning_top_bot": "bot",
    "score": "4-1",
    "batting": "N.C. A&T",
    "fielding": "Dayton",
    "description": "SEATON, A. struck out swinging.",
    "year": 2022,
    "game_pbp_url": "https://stats.ncaa.org/game/play_by_play/5209055",
    "game_pbp_id": 5209055
  },
  {
    "game_date": "02/19/2022",
    "location": "Greensboro, NC",
    "inning": "4",
    "inning_top_bot": "top",
    "score": "4-1",
    "batting": "Dayton",
    "fielding": "N.C. A&T",
    "description": "CALERO walked.",
    "year": 2022,
    "game_pbp_url": "https://stats.ncaa.org/game/play_by_play/5209055",
    "game_pbp_id": 5209055
  },
  {
    "game_date": "02/19/2022",
    "location": "Greensboro, NC",
    "inning": "4",
    "inning_top_bot": "top",
    "score": "4-1",
    "batting": "Dayton",
    "fielding": "N.C. A&T",
    "description": "CALERO advanced to second on a wild pitch.",
    "year": 2022,
    "game_pbp_url": "https://stats.ncaa.org/game/play_by_play/5209055",
    "game_pbp_id": 5209055
  },
  {
    "game_date": "02/19/2022",
    "location": "Greensboro, NC",
    "inning": "4",
    "inning_top_bot": "top",
    "score": "4-1",
    "batting": "Dayton",
    "fielding": "N.C. A&T",
    "description": "DANIELS walked.",
    "year": 2022,
    "game_pbp_url": "https://stats.ncaa.org/game/play_by_play/5209055",
    "game_pbp_id": 5209055
  },
  {
    "game_date": "02/19/2022",
    "location": "Greensboro, NC",
    "inning": "4",
    "inning_top_bot": "top",
    "score": "4-1",
    "batting": "Dayton",
    "fielding": "N.C. A&T",
    "description": "DEMURIAS, E. to p for HULL, J..",
    "year": 2022,
    "game_pbp_url": "https://stats.ncaa.org/game/play_by_play/5209055",
    "game_pbp_id": 5209055
  },
  {
    "game_date": "02/19/2022",
    "location": "Greensboro, NC",
    "inning": "4",
    "inning_top_bot": "top",
    "score": "4-1",
    "batting": "Dayton",
    "fielding": "N.C. A&T",
    "description": "MARTINEZ struck out swinging.",
    "year": 2022,
    "game_pbp_url": "https://stats.ncaa.org/game/play_by_play/5209055",
    "game_pbp_id": 5209055
  },
  {
    "game_date": "02/19/2022",
    "location": "Greensboro, NC",
    "inning": "4",
    "inning_top_bot": "top",
    "score": "4-1",
    "batting": "Dayton",
    "fielding": "N.C. A&T",
    "description": "JONES reached on a fielder's choice3a DANIELS advanced to second3a CALERO out at third 3b unassisted.",
    "year": 2022,
    "game_pbp_url": "https://stats.ncaa.org/game/play_by_play/5209055",
    "game_pbp_id": 5209055
  },
  {
    "game_date": "02/19/2022",
    "location": "Greensboro, NC",
    "inning": "4",
    "inning_top_bot": "top",
    "score": "4-1",
    "batting": "Dayton",
    "fielding": "N.C. A&T",
    "description": "PUJOLS flied out to 3b.",
    "year": 2022,
    "game_pbp_url": "https://stats.ncaa.org/game/play_by_play/5209055",
    "game_pbp_id": 5209055
  },
  {
    "game_date": "02/19/2022",
    "location": "Greensboro, NC",
    "inning": "4",
    "inning_top_bot": "top",
    "score": "4-1",
    "batting": "Dayton",
    "fielding": "N.C. A&T",
    "description": "LOB: 2",
    "year": 2022,
    "game_pbp_url": "https://stats.ncaa.org/game/play_by_play/5209055",
    "game_pbp_id": 5209055
  },
  {
    "game_date": "02/19/2022",
    "location": "Greensboro, NC",
    "inning": "4",
    "inning_top_bot": "bot",
    "score": "4-1",
    "batting": "N.C. A&T",
    "fielding": "Dayton",
    "description": "REYNA, A. out at first 1b to p.",
    "year": 2022,
    "game_pbp_url": "https://stats.ncaa.org/game/play_by_play/5209055",
    "game_pbp_id": 5209055
  },
  {
    "game_date": "02/19/2022",
    "location": "Greensboro, NC",
    "inning": "4",
    "inning_top_bot": "bot",
    "score": "4-1",
    "batting": "N.C. A&T",
    "fielding": "Dayton",
    "description": "BROWN, C. struck out looking.",
    "year": 2022,
    "game_pbp_url": "https://stats.ncaa.org/game/play_by_play/5209055",
    "game_pbp_id": 5209055
  },
  {
    "game_date": "02/19/2022",
    "location": "Greensboro, NC",
    "inning": "4",
    "inning_top_bot": "bot",
    "score": "4-1",
    "batting": "N.C. A&T",
    "fielding": "Dayton",
    "description": "BRANTLEY, C. hit by pitch.",
    "year": 2022,
    "game_pbp_url": "https://stats.ncaa.org/game/play_by_play/5209055",
    "game_pbp_id": 5209055
  },
  {
    "game_date": "02/19/2022",
    "location": "Greensboro, NC",
    "inning": "4",
    "inning_top_bot": "bot",
    "score": "4-1",
    "batting": "N.C. A&T",
    "fielding": "Dayton",
    "description": "MAYNARD, C. walked3a BRANTLEY, C. advanced to second.",
    "year": 2022,
    "game_pbp_url": "https://stats.ncaa.org/game/play_by_play/5209055",
    "game_pbp_id": 5209055
  },
  {
    "game_date": "02/19/2022",
    "location": "Greensboro, NC",
    "inning": "4",
    "inning_top_bot": "bot",
    "score": "4-1",
    "batting": "N.C. A&T",
    "fielding": "Dayton",
    "description": "JACKSON, C. grounded out to 2b.",
    "year": 2022,
    "game_pbp_url": "https://stats.ncaa.org/game/play_by_play/5209055",
    "game_pbp_id": 5209055
  },
  {
    "game_date": "02/19/2022",
    "location": "Greensboro, NC",
    "inning": "4",
    "inning_top_bot": "top",
    "score": "4-1",
    "batting": "Dayton",
    "fielding": "N.C. A&T",
    "description": "LOB: 2",
    "year": 2022,
    "game_pbp_url": "https://stats.ncaa.org/game/play_by_play/5209055",
    "game_pbp_id": 5209055
  },
  {
    "game_date": "02/19/2022",
    "location": "Greensboro, NC",
    "inning": "5",
    "inning_top_bot": "top",
    "score": "4-1",
    "batting": "Dayton",
    "fielding": "N.C. A&T",
    "description": "STRMECKI flied out to cf.",
    "year": 2022,
    "game_pbp_url": "https://stats.ncaa.org/game/play_by_play/5209055",
    "game_pbp_id": 5209055
  },
  {
    "game_date": "02/19/2022",
    "location": "Greensboro, NC",
    "inning": "5",
    "inning_top_bot": "top",
    "score": "4-1",
    "batting": "Dayton",
    "fielding": "N.C. A&T",
    "description": "NEFF struck out swinging.",
    "year": 2022,
    "game_pbp_url": "https://stats.ncaa.org/game/play_by_play/5209055",
    "game_pbp_id": 5209055
  },
  {
    "game_date": "02/19/2022",
    "location": "Greensboro, NC",
    "inning": "5",
    "inning_top_bot": "top",
    "score": "4-1",
    "batting": "Dayton",
    "fielding": "N.C. A&T",
    "description": "CURTIS flied out to rf.",
    "year": 2022,
    "game_pbp_url": "https://stats.ncaa.org/game/play_by_play/5209055",
    "game_pbp_id": 5209055
  },
  {
    "game_date": "02/19/2022",
    "location": "Greensboro, NC",
    "inning": "5",
    "inning_top_bot": "bot",
    "score": "4-1",
    "batting": "N.C. A&T",
    "fielding": "Dayton",
    "description": "BUSSEY, X. tripled through the right side.",
    "year": 2022,
    "game_pbp_url": "https://stats.ncaa.org/game/play_by_play/5209055",
    "game_pbp_id": 5209055
  },
  {
    "game_date": "02/19/2022",
    "location": "Greensboro, NC",
    "inning": "5",
    "inning_top_bot": "bot",
    "score": "4-1",
    "batting": "N.C. A&T",
    "fielding": "Dayton",
    "description": "BARRETT, T. walked.",
    "year": 2022,
    "game_pbp_url": "https://stats.ncaa.org/game/play_by_play/5209055",
    "game_pbp_id": 5209055
  },
  {
    "game_date": "02/19/2022",
    "location": "Greensboro, NC",
    "inning": "5",
    "inning_top_bot": "bot",
    "score": "4-1",
    "batting": "N.C. A&T",
    "fielding": "Dayton",
    "description": "HATTRUP to p for STEINHAUER.",
    "year": 2022,
    "game_pbp_url": "https://stats.ncaa.org/game/play_by_play/5209055",
    "game_pbp_id": 5209055
  },
  {
    "game_date": "02/19/2022",
    "location": "Greensboro, NC",
    "inning": "5",
    "inning_top_bot": "bot",
    "score": "4-2",
    "batting": "N.C. A&T",
    "fielding": "Dayton",
    "description": "SIKES, C. hit into double play 2b to ss to 1b3a BARRETT, T. out on the play3a BUSSEY, X. scored.",
    "year": 2022,
    "game_pbp_url": "https://stats.ncaa.org/game/play_by_play/5209055",
    "game_pbp_id": 5209055
  },
  {
    "game_date": "02/19/2022",
    "location": "Greensboro, NC",
    "inning": "5",
    "inning_top_bot": "bot",
    "score": "4-2",
    "batting": "N.C. A&T",
    "fielding": "Dayton",
    "description": "SEATON, A. reached on a fielding error by lf, advanced to second.",
    "year": 2022,
    "game_pbp_url": "https://stats.ncaa.org/game/play_by_play/5209055",
    "game_pbp_id": 5209055
  },
  {
    "game_date": "02/19/2022",
    "location": "Greensboro, NC",
    "inning": "5",
    "inning_top_bot": "bot",
    "score": "4-3",
    "batting": "N.C. A&T",
    "fielding": "Dayton",
    "description": "REYNA, A. singled to right field, RBI3a SEATON, A. scored, unearned.",
    "year": 2022,
    "game_pbp_url": "https://stats.ncaa.org/game/play_by_play/5209055",
    "game_pbp_id": 5209055
  },
  {
    "game_date": "02/19/2022",
    "location": "Greensboro, NC",
    "inning": "5",
    "inning_top_bot": "bot",
    "score": "4-3",
    "batting": "N.C. A&T",
    "fielding": "Dayton",
    "description": "BROWN, C. walked3a REYNA, A. advanced to second.",
    "year": 2022,
    "game_pbp_url": "https://stats.ncaa.org/game/play_by_play/5209055",
    "game_pbp_id": 5209055
  },
  {
    "game_date": "02/19/2022",
    "location": "Greensboro, NC",
    "inning": "5",
    "inning_top_bot": "bot",
    "score": "4-3",
    "batting": "N.C. A&T",
    "fielding": "Dayton",
    "description": "WHITTEN to p for HATTRUP.",
    "year": 2022,
    "game_pbp_url": "https://stats.ncaa.org/game/play_by_play/5209055",
    "game_pbp_id": 5209055
  },
  {
    "game_date": "02/19/2022",
    "location": "Greensboro, NC",
    "inning": "5",
    "inning_top_bot": "bot",
    "score": "4-3",
    "batting": "N.C. A&T",
    "fielding": "Dayton",
    "description": "REYNA, A. out at third c to 3b, caught stealing.",
    "year": 2022,
    "game_pbp_url": "https://stats.ncaa.org/game/play_by_play/5209055",
    "game_pbp_id": 5209055
  },
  {
    "game_date": "02/19/2022",
    "location": "Greensboro, NC",
    "inning": "5",
    "inning_top_bot": "bot",
    "score": "4-3",
    "batting": "N.C. A&T",
    "fielding": "Dayton",
    "description": "R: 2 H: 2 E: 1 LOB: 1",
    "year": 2022,
    "game_pbp_url": "https://stats.ncaa.org/game/play_by_play/5209055",
    "game_pbp_id": 5209055
  },
  {
    "game_date": "02/19/2022",
    "location": "Greensboro, NC",
    "inning": "6",
    "inning_top_bot": "top",
    "score": "4-3",
    "batting": "Dayton",
    "fielding": "N.C. A&T",
    "description": "CASTILLO reached on a fielding error by 1b, advanced to second.",
    "year": 2022,
    "game_pbp_url": "https://stats.ncaa.org/game/play_by_play/5209055",
    "game_pbp_id": 5209055
  },
  {
    "game_date": "02/19/2022",
    "location": "Greensboro, NC",
    "inning": "6",
    "inning_top_bot": "top",
    "score": "4-3",
    "batting": "Dayton",
    "fielding": "N.C. A&T",
    "description": "CALERO reached on a throwing error by 3b.",
    "year": 2022,
    "game_pbp_url": "https://stats.ncaa.org/game/play_by_play/5209055",
    "game_pbp_id": 5209055
  },
  {
    "game_date": "02/19/2022",
    "location": "Greensboro, NC",
    "inning": "6",
    "inning_top_bot": "top",
    "score": "5-3",
    "batting": "Dayton",
    "fielding": "N.C. A&T",
    "description": "DANIELS reached on a throwing error by p, SAC, advanced to second3a CALERO advanced to third3a CASTILLO scored, unearned.",
    "year": 2022,
    "game_pbp_url": "https://stats.ncaa.org/game/play_by_play/5209055",
    "game_pbp_id": 5209055
  },
  {
    "game_date": "02/19/2022",
    "location": "Greensboro, NC",
    "inning": "6",
    "inning_top_bot": "top",
    "score": "6-3",
    "batting": "Dayton",
    "fielding": "N.C. A&T",
    "description": "MARTINEZ walked3a DANIELS advanced to third3a CALERO scored on a passed ball, unearned.",
    "year": 2022,
    "game_pbp_url": "https://stats.ncaa.org/game/play_by_play/5209055",
    "game_pbp_id": 5209055
  },
  {
    "game_date": "02/19/2022",
    "location": "Greensboro, NC",
    "inning": "6",
    "inning_top_bot": "top",
    "score": "6-3",
    "batting": "Dayton",
    "fielding": "N.C. A&T",
    "description": "THOMAS, S. to p for DEMURIAS, E..",
    "year": 2022,
    "game_pbp_url": "https://stats.ncaa.org/game/play_by_play/5209055",
    "game_pbp_id": 5209055
  },
  {
    "game_date": "02/19/2022",
    "location": "Greensboro, NC",
    "inning": "6",
    "inning_top_bot": "top",
    "score": "7-3",
    "batting": "Dayton",
    "fielding": "N.C. A&T",
    "description": "JONES flied out to cf, SAC, RBI3a MARTINEZ advanced to second3a DANIELS scored, unearned.",
    "year": 2022,
    "game_pbp_url": "https://stats.ncaa.org/game/play_by_play/5209055",
    "game_pbp_id": 5209055
  },
  {
    "game_date": "02/19/2022",
    "location": "Greensboro, NC",
    "inning": "6",
    "inning_top_bot": "top",
    "score": "7-3",
    "batting": "Dayton",
    "fielding": "N.C. A&T",
    "description": "PUJOLS walked.",
    "year": 2022,
    "game_pbp_url": "https://stats.ncaa.org/game/play_by_play/5209055",
    "game_pbp_id": 5209055
  },
  {
    "game_date": "02/19/2022",
    "location": "Greensboro, NC",
    "inning": "6",
    "inning_top_bot": "top",
    "score": "7-3",
    "batting": "Dayton",
    "fielding": "N.C. A&T",
    "description": "STRMECKI hit by pitch3a PUJOLS advanced to second3a MARTINEZ advanced to third.",
    "year": 2022,
    "game_pbp_url": "https://stats.ncaa.org/game/play_by_play/5209055",
    "game_pbp_id": 5209055
  },
  {
    "game_date": "02/19/2022",
    "location": "Greensboro, NC",
    "inning": "6",
    "inning_top_bot": "top",
    "score": "7-3",
    "batting": "Dayton",
    "fielding": "N.C. A&T",
    "description": "NEFF struck out looking.",
    "year": 2022,
    "game_pbp_url": "https://stats.ncaa.org/game/play_by_play/5209055",
    "game_pbp_id": 5209055
  },
  {
    "game_date": "02/19/2022",
    "location": "Greensboro, NC",
    "inning": "6",
    "inning_top_bot": "top",
    "score": "8-3",
    "batting": "Dayton",
    "fielding": "N.C. A&T",
    "description": "STRMECKI advanced to second3a PUJOLS advanced to third3a MARTINEZ scored on a passed ball, unearned.",
    "year": 2022,
    "game_pbp_url": "https://stats.ncaa.org/game/play_by_play/5209055",
    "game_pbp_id": 5209055
  },
  {
    "game_date": "02/19/2022",
    "location": "Greensboro, NC",
    "inning": "6",
    "inning_top_bot": "top",
    "score": "8-3",
    "batting": "Dayton",
    "fielding": "N.C. A&T",
    "description": "CURTIS walked.",
    "year": 2022,
    "game_pbp_url": "https://stats.ncaa.org/game/play_by_play/5209055",
    "game_pbp_id": 5209055
  },
  {
    "game_date": "02/19/2022",
    "location": "Greensboro, NC",
    "inning": "6",
    "inning_top_bot": "top",
    "score": "8-3",
    "batting": "Dayton",
    "fielding": "N.C. A&T",
    "description": "CASTILLO reached on a fielder's choice3a CURTIS out at second ss to 2b.",
    "year": 2022,
    "game_pbp_url": "https://stats.ncaa.org/game/play_by_play/5209055",
    "game_pbp_id": 5209055
  },
  {
    "game_date": "02/19/2022",
    "location": "Greensboro, NC",
    "inning": "6",
    "inning_top_bot": "bot",
    "score": "8-3",
    "batting": "N.C. A&T",
    "fielding": "Dayton",
    "description": "BRANTLEY, C. walked.",
    "year": 2022,
    "game_pbp_url": "https://stats.ncaa.org/game/play_by_play/5209055",
    "game_pbp_id": 5209055
  },
  {
    "game_date": "02/19/2022",
    "location": "Greensboro, NC",
    "inning": "6",
    "inning_top_bot": "bot",
    "score": "8-3",
    "batting": "N.C. A&T",
    "fielding": "Dayton",
    "description": "BRANTLEY, C. out at second c to ss, caught stealing.",
    "year": 2022,
    "game_pbp_url": "https://stats.ncaa.org/game/play_by_play/5209055",
    "game_pbp_id": 5209055
  },
  {
    "game_date": "02/19/2022",
    "location": "Greensboro, NC",
    "inning": "6",
    "inning_top_bot": "bot",
    "score": "8-3",
    "batting": "N.C. A&T",
    "fielding": "Dayton",
    "description": "MAYNARD, C. reached on a fielding error by ss.",
    "year": 2022,
    "game_pbp_url": "https://stats.ncaa.org/game/play_by_play/5209055",
    "game_pbp_id": 5209055
  },
  {
    "game_date": "02/19/2022",
    "location": "Greensboro, NC",
    "inning": "6",
    "inning_top_bot": "bot",
    "score": "8-3",
    "batting": "N.C. A&T",
    "fielding": "Dayton",
    "description": "JACKSON, C. reached on a fielding error by ss3a MAYNARD, C. advanced to second.",
    "year": 2022,
    "game_pbp_url": "https://stats.ncaa.org/game/play_by_play/5209055",
    "game_pbp_id": 5209055
  },
  {
    "game_date": "02/19/2022",
    "location": "Greensboro, NC",
    "inning": "6",
    "inning_top_bot": "bot",
    "score": "8-3",
    "batting": "N.C. A&T",
    "fielding": "Dayton",
    "description": "MAUE to p for WHITTEN.",
    "year": 2022,
    "game_pbp_url": "https://stats.ncaa.org/game/play_by_play/5209055",
    "game_pbp_id": 5209055
  },
  {
    "game_date": "02/19/2022",
    "location": "Greensboro, NC",
    "inning": "6",
    "inning_top_bot": "bot",
    "score": "8-3",
    "batting": "N.C. A&T",
    "fielding": "Dayton",
    "description": "JACKSON, C. advanced to second3a MAYNARD, C. advanced to third on a wild pitch.",
    "year": 2022,
    "game_pbp_url": "https://stats.ncaa.org/game/play_by_play/5209055",
    "game_pbp_id": 5209055
  },
  {
    "game_date": "02/19/2022",
    "location": "Greensboro, NC",
    "inning": "6",
    "inning_top_bot": "bot",
    "score": "8-4",
    "batting": "N.C. A&T",
    "fielding": "Dayton",
    "description": "BUSSEY, X. grounded out to 3b, RBI3a JACKSON, C. no advance3a MAYNARD, C. scored, unearned.",
    "year": 2022,
    "game_pbp_url": "https://stats.ncaa.org/game/play_by_play/5209055",
    "game_pbp_id": 5209055
  },
  {
    "game_date": "02/19/2022",
    "location": "Greensboro, NC",
    "inning": "6",
    "inning_top_bot": "bot",
    "score": "8-4",
    "batting": "N.C. A&T",
    "fielding": "Dayton",
    "description": "BARRETT, T. walked.",
    "year": 2022,
    "game_pbp_url": "https://stats.ncaa.org/game/play_by_play/5209055",
    "game_pbp_id": 5209055
  },
  {
    "game_date": "02/19/2022",
    "location": "Greensboro, NC",
    "inning": "6",
    "inning_top_bot": "bot",
    "score": "8-4",
    "batting": "N.C. A&T",
    "fielding": "Dayton",
    "description": "SIKES, C. struck out looking.",
    "year": 2022,
    "game_pbp_url": "https://stats.ncaa.org/game/play_by_play/5209055",
    "game_pbp_id": 5209055
  },
  {
    "game_date": "02/19/2022",
    "location": "Greensboro, NC",
    "inning": "7",
    "inning_top_bot": "top",
    "score": "8-4",
    "batting": "Dayton",
    "fielding": "N.C. A&T",
    "description": "CRAYTON, M. to p for THOMAS, S..",
    "year": 2022,
    "game_pbp_url": "https://stats.ncaa.org/game/play_by_play/5209055",
    "game_pbp_id": 5209055
  },
  {
    "game_date": "02/19/2022",
    "location": "Greensboro, NC",
    "inning": "7",
    "inning_top_bot": "top",
    "score": "8-4",
    "batting": "Dayton",
    "fielding": "N.C. A&T",
    "description": "CALERO popped up to 2b.",
    "year": 2022,
    "game_pbp_url": "https://stats.ncaa.org/game/play_by_play/5209055",
    "game_pbp_id": 5209055
  },
  {
    "game_date": "02/19/2022",
    "location": "Greensboro, NC",
    "inning": "7",
    "inning_top_bot": "top",
    "score": "8-4",
    "batting": "Dayton",
    "fielding": "N.C. A&T",
    "description": "DANIELS struck out looking.",
    "year": 2022,
    "game_pbp_url": "https://stats.ncaa.org/game/play_by_play/5209055",
    "game_pbp_id": 5209055
  },
  {
    "game_date": "02/19/2022",
    "location": "Greensboro, NC",
    "inning": "7",
    "inning_top_bot": "top",
    "score": "8-4",
    "batting": "Dayton",
    "fielding": "N.C. A&T",
    "description": "MARTINEZ hit by pitch.",
    "year": 2022,
    "game_pbp_url": "https://stats.ncaa.org/game/play_by_play/5209055",
    "game_pbp_id": 5209055
  },
  {
    "game_date": "02/19/2022",
    "location": "Greensboro, NC",
    "inning": "7",
    "inning_top_bot": "top",
    "score": "8-4",
    "batting": "Dayton",
    "fielding": "N.C. A&T",
    "description": "MARTINEZ out at second c to ss, caught stealing.",
    "year": 2022,
    "game_pbp_url": "https://stats.ncaa.org/game/play_by_play/5209055",
    "game_pbp_id": 5209055
  },
  {
    "game_date": "02/19/2022",
    "location": "Greensboro, NC",
    "inning": "7",
    "inning_top_bot": "bot",
    "score": "8-4",
    "batting": "N.C. A&T",
    "fielding": "Dayton",
    "description": "SEATON, A. singled to left field.",
    "year": 2022,
    "game_pbp_url": "https://stats.ncaa.org/game/play_by_play/5209055",
    "game_pbp_id": 5209055
  },
  {
    "game_date": "02/19/2022",
    "location": "Greensboro, NC",
    "inning": "7",
    "inning_top_bot": "bot",
    "score": "8-4",
    "batting": "N.C. A&T",
    "fielding": "Dayton",
    "description": "MAJICK to p for MAUE.",
    "year": 2022,
    "game_pbp_url": "https://stats.ncaa.org/game/play_by_play/5209055",
    "game_pbp_id": 5209055
  },
  {
    "game_date": "02/19/2022",
    "location": "Greensboro, NC",
    "inning": "7",
    "inning_top_bot": "bot",
    "score": "8-4",
    "batting": "N.C. A&T",
    "fielding": "Dayton",
    "description": "REYNA, A. singled through the right side3a SEATON, A. advanced to second.",
    "year": 2022,
    "game_pbp_url": "https://stats.ncaa.org/game/play_by_play/5209055",
    "game_pbp_id": 5209055
  },
  {
    "game_date": "02/19/2022",
    "location": "Greensboro, NC",
    "inning": "7",
    "inning_top_bot": "bot",
    "score": "8-4",
    "batting": "N.C. A&T",
    "fielding": "Dayton",
    "description": "BARD to p for MAJICK.",
    "year": 2022,
    "game_pbp_url": "https://stats.ncaa.org/game/play_by_play/5209055",
    "game_pbp_id": 5209055
  },
  {
    "game_date": "02/19/2022",
    "location": "Greensboro, NC",
    "inning": "7",
    "inning_top_bot": "bot",
    "score": "8-4",
    "batting": "N.C. A&T",
    "fielding": "Dayton",
    "description": "BROWN, C. hit by pitch3a REYNA, A. advanced to second3a SEATON, A. advanced to third.",
    "year": 2022,
    "game_pbp_url": "https://stats.ncaa.org/game/play_by_play/5209055",
    "game_pbp_id": 5209055
  },
  {
    "game_date": "02/19/2022",
    "location": "Greensboro, NC",
    "inning": "7",
    "inning_top_bot": "bot",
    "score": "8-4",
    "batting": "N.C. A&T",
    "fielding": "Dayton",
    "description": "BRANTLEY, C. fouled out to 3b.",
    "year": 2022,
    "game_pbp_url": "https://stats.ncaa.org/game/play_by_play/5209055",
    "game_pbp_id": 5209055
  },
  {
    "game_date": "02/19/2022",
    "location": "Greensboro, NC",
    "inning": "7",
    "inning_top_bot": "bot",
    "score": "8-4",
    "batting": "N.C. A&T",
    "fielding": "Dayton",
    "description": "MAYNARD, C. struck out looking.",
    "year": 2022,
    "game_pbp_url": "https://stats.ncaa.org/game/play_by_play/5209055",
    "game_pbp_id": 5209055
  },
  {
    "game_date": "02/19/2022",
    "location": "Greensboro, NC",
    "inning": "7",
    "inning_top_bot": "bot",
    "score": "8-4",
    "batting": "N.C. A&T",
    "fielding": "Dayton",
    "description": "JACKSON, C. struck out swinging.",
    "year": 2022,
    "game_pbp_url": "https://stats.ncaa.org/game/play_by_play/5209055",
    "game_pbp_id": 5209055
  },
  {
    "game_date": "02/19/2022",
    "location": "Greensboro, NC",
    "inning": "7",
    "inning_top_bot": "bot",
    "score": "8-4",
    "batting": "N.C. A&T",
    "fielding": "Dayton",
    "description": "H: 2 LOB: 3",
    "year": 2022,
    "game_pbp_url": "https://stats.ncaa.org/game/play_by_play/5209055",
    "game_pbp_id": 5209055
  },
  {
    "game_date": "02/19/2022",
    "location": "Greensboro, NC",
    "inning": "8",
    "inning_top_bot": "top",
    "score": "8-4",
    "batting": "Dayton",
    "fielding": "N.C. A&T",
    "description": "BREWINGTON, to p for CRAYTON, M..",
    "year": 2022,
    "game_pbp_url": "https://stats.ncaa.org/game/play_by_play/5209055",
    "game_pbp_id": 5209055
  },
  {
    "game_date": "02/19/2022",
    "location": "Greensboro, NC",
    "inning": "8",
    "inning_top_bot": "top",
    "score": "8-4",
    "batting": "Dayton",
    "fielding": "N.C. A&T",
    "description": "JONES grounded out to 3b.",
    "year": 2022,
    "game_pbp_url": "https://stats.ncaa.org/game/play_by_play/5209055",
    "game_pbp_id": 5209055
  },
  {
    "game_date": "02/19/2022",
    "location": "Greensboro, NC",
    "inning": "8",
    "inning_top_bot": "top",
    "score": "8-4",
    "batting": "Dayton",
    "fielding": "N.C. A&T",
    "description": "PUJOLS flied out to lf.",
    "year": 2022,
    "game_pbp_url": "https://stats.ncaa.org/game/play_by_play/5209055",
    "game_pbp_id": 5209055
  },
  {
    "game_date": "02/19/2022",
    "location": "Greensboro, NC",
    "inning": "8",
    "inning_top_bot": "top",
    "score": "9-4",
    "batting": "Dayton",
    "fielding": "N.C. A&T",
    "description": "STRMECKI homered to left field, RBI.",
    "year": 2022,
    "game_pbp_url": "https://stats.ncaa.org/game/play_by_play/5209055",
    "game_pbp_id": 5209055
  },
  {
    "game_date": "02/19/2022",
    "location": "Greensboro, NC",
    "inning": "8",
    "inning_top_bot": "top",
    "score": "9-4",
    "batting": "Dayton",
    "fielding": "N.C. A&T",
    "description": "NEFF struck out looking.",
    "year": 2022,
    "game_pbp_url": "https://stats.ncaa.org/game/play_by_play/5209055",
    "game_pbp_id": 5209055
  },
  {
    "game_date": "02/19/2022",
    "location": "Greensboro, NC",
    "inning": "8",
    "inning_top_bot": "bot",
    "score": "9-4",
    "batting": "N.C. A&T",
    "fielding": "Dayton",
    "description": "BUSSEY, X. popped up to ss.",
    "year": 2022,
    "game_pbp_url": "https://stats.ncaa.org/game/play_by_play/5209055",
    "game_pbp_id": 5209055
  },
  {
    "game_date": "02/19/2022",
    "location": "Greensboro, NC",
    "inning": "8",
    "inning_top_bot": "bot",
    "score": "9-4",
    "batting": "N.C. A&T",
    "fielding": "Dayton",
    "description": "BARRETT, T. walked.",
    "year": 2022,
    "game_pbp_url": "https://stats.ncaa.org/game/play_by_play/5209055",
    "game_pbp_id": 5209055
  },
  {
    "game_date": "02/19/2022",
    "location": "Greensboro, NC",
    "inning": "8",
    "inning_top_bot": "bot",
    "score": "9-4",
    "batting": "N.C. A&T",
    "fielding": "Dayton",
    "description": "SIKES, C. walked3a BARRETT, T. advanced to second.",
    "year": 2022,
    "game_pbp_url": "https://stats.ncaa.org/game/play_by_play/5209055",
    "game_pbp_id": 5209055
  },
  {
    "game_date": "02/19/2022",
    "location": "Greensboro, NC",
    "inning": "8",
    "inning_top_bot": "bot",
    "score": "9-4",
    "batting": "N.C. A&T",
    "fielding": "Dayton",
    "description": "ZAPKA to p for BARD.",
    "year": 2022,
    "game_pbp_url": "https://stats.ncaa.org/game/play_by_play/5209055",
    "game_pbp_id": 5209055
  },
  {
    "game_date": "02/19/2022",
    "location": "Greensboro, NC",
    "inning": "8",
    "inning_top_bot": "bot",
    "score": "9-4",
    "batting": "N.C. A&T",
    "fielding": "Dayton",
    "description": "SEATON, A. struck out looking.",
    "year": 2022,
    "game_pbp_url": "https://stats.ncaa.org/game/play_by_play/5209055",
    "game_pbp_id": 5209055
  },
  {
    "game_date": "02/19/2022",
    "location": "Greensboro, NC",
    "inning": "8",
    "inning_top_bot": "bot",
    "score": "9-6",
    "batting": "N.C. A&T",
    "fielding": "Dayton",
    "description": "REYNA, A. reached on an error by lf, advanced to third3a SIKES, C. scored, unearned3a BARRETT, T. scored, unearned.",
    "year": 2022,
    "game_pbp_url": "https://stats.ncaa.org/game/play_by_play/5209055",
    "game_pbp_id": 5209055
  },
  {
    "game_date": "02/19/2022",
    "location": "Greensboro, NC",
    "inning": "8",
    "inning_top_bot": "bot",
    "score": "9-6",
    "batting": "N.C. A&T",
    "fielding": "Dayton",
    "description": "REYNA, A. out at home c to p.",
    "year": 2022,
    "game_pbp_url": "https://stats.ncaa.org/game/play_by_play/5209055",
    "game_pbp_id": 5209055
  },
  {
    "game_date": "02/19/2022",
    "location": "Greensboro, NC",
    "inning": "9",
    "inning_top_bot": "top",
    "score": "9-6",
    "batting": "Dayton",
    "fielding": "N.C. A&T",
    "description": "CURTIS flied out to cf.",
    "year": 2022,
    "game_pbp_url": "https://stats.ncaa.org/game/play_by_play/5209055",
    "game_pbp_id": 5209055
  },
  {
    "game_date": "02/19/2022",
    "location": "Greensboro, NC",
    "inning": "9",
    "inning_top_bot": "top",
    "score": "9-6",
    "batting": "Dayton",
    "fielding": "N.C. A&T",
    "description": "CASTILLO struck out swinging.",
    "year": 2022,
    "game_pbp_url": "https://stats.ncaa.org/game/play_by_play/5209055",
    "game_pbp_id": 5209055
  },
  {
    "game_date": "02/19/2022",
    "location": "Greensboro, NC",
    "inning": "9",
    "inning_top_bot": "top",
    "score": "9-6",
    "batting": "Dayton",
    "fielding": "N.C. A&T",
    "description": "CALERO struck out looking.",
    "year": 2022,
    "game_pbp_url": "https://stats.ncaa.org/game/play_by_play/5209055",
    "game_pbp_id": 5209055
  },
  {
    "game_date": "02/19/2022",
    "location": "Greensboro, NC",
    "inning": "9",
    "inning_top_bot": "bot",
    "score": "9-6",
    "batting": "N.C. A&T",
    "fielding": "Dayton",
    "description": "BROWN, C. singled through the left side.",
    "year": 2022,
    "game_pbp_url": "https://stats.ncaa.org/game/play_by_play/5209055",
    "game_pbp_id": 5209055
  },
  {
    "game_date": "02/19/2022",
    "location": "Greensboro, NC",
    "inning": "9",
    "inning_top_bot": "bot",
    "score": "9-6",
    "batting": "N.C. A&T",
    "fielding": "Dayton",
    "description": "BRANTLEY, C. singled to right center3a BROWN, C. advanced to second.",
    "year": 2022,
    "game_pbp_url": "https://stats.ncaa.org/game/play_by_play/5209055",
    "game_pbp_id": 5209055
  },
  {
    "game_date": "02/19/2022",
    "location": "Greensboro, NC",
    "inning": "9",
    "inning_top_bot": "bot",
    "score": "9-6",
    "batting": "N.C. A&T",
    "fielding": "Dayton",
    "description": "MAYNARD, C. hit into double play ss to 2b to 1b3a BRANTLEY, C. out on the play3a BROWN, C. advanced to third.",
    "year": 2022,
    "game_pbp_url": "https://stats.ncaa.org/game/play_by_play/5209055",
    "game_pbp_id": 5209055
  },
  {
    "game_date": "02/19/2022",
    "location": "Greensboro, NC",
    "inning": "9",
    "inning_top_bot": "bot",
    "score": "9-7",
    "batting": "N.C. A&T",
    "fielding": "Dayton",
    "description": "JACKSON, C. reached on an error by 2b3a BROWN, C. scored, unearned.",
    "year": 2022,
    "game_pbp_url": "https://stats.ncaa.org/game/play_by_play/5209055",
    "game_pbp_id": 5209055
  },
  {
    "game_date": "02/19/2022",
    "location": "Greensboro, NC",
    "inning": "9",
    "inning_top_bot": "bot",
    "score": "9-7",
    "batting": "N.C. A&T",
    "fielding": "Dayton",
    "description": "BUSSEY, X. struck out swinging.",
    "year": 2022,
    "game_pbp_url": "https://stats.ncaa.org/game/play_by_play/5209055",
    "game_pbp_id": 5209055
  },
  {
    "game_date": "02/19/2022",
    "location": "Greensboro, NC",
    "inning": "9",
    "inning_top_bot": "bot",
    "score": "9-7",
    "batting": "N.C. A&T",
    "fielding": "Dayton",
    "description": "R: 1 H: 2 E: 1 LOB: 1",
    "year": 2022,
    "game_pbp_url": "https://stats.ncaa.org/game/play_by_play/5209055",
    "game_pbp_id": 5209055
  }
]

